argskwargs.py
argskwargs-1.0.3.dist-info/DESCRIPTION.rst
argskwargs-1.0.3.dist-info/LICENSE.txt
argskwargs-1.0.3.dist-info/METADATA
argskwargs-1.0.3.dist-info/RECORD
argskwargs-1.0.3.dist-info/WHEEL
argskwargs-1.0.3.dist-info/metadata.json
argskwargs-1.0.3.dist-info/top_level.txt
