Metadata-Version: 2.0
Name: argskwargs
Version: 1.0.3
Summary: flexible container for positional and keyword arguments
Home-page: https://github.com/wbolster/argskwargs
Author: Wouter Bolsterlee
Author-email: wouter@bolsterl.ee
License: BSD
Platform: UNKNOWN
Classifier: Development Status :: 5 - Production/Stable
Classifier: Intended Audience :: Developers
Classifier: License :: OSI Approved :: BSD License
Classifier: Programming Language :: Python
Classifier: Programming Language :: Python :: 2
Classifier: Programming Language :: Python :: 3
Classifier: Topic :: Software Development :: Libraries
Classifier: Topic :: Software Development :: Libraries :: Python Modules
